{
  "schema_id": "alexandrian-academy.enums.lifecycle-states.v1",
  "version": "1.0.0",
  "states": [
    {
      "token": "draft",
      "conceptual_aliases": ["sandbox"],
      "description": "Work-in-progress objects. Valid for iteration, not promoted."
    },
    {
      "token": "accepted",
      "conceptual_aliases": ["canon"],
      "description": "Promoted objects. Must satisfy strict evidence, standards, and jurisdiction gates."
    }
  ],
  "transitions": [
    { "from": "draft", "to": "accepted", "requires": ["changeset", "evidence", "standards", "jurisdiction"] },
    { "from": "accepted", "to": "draft", "requires": ["changeset", "revert_justification"] }
  ]
}
